vexor/__init__.py
vexor/__main__.py
vexor/api.py
vexor/cache.py
vexor/cli.py
vexor/config.py
vexor/modes.py
vexor/output.py
vexor/search.py
vexor/text.py
vexor/utils.py
vexor/providers/__init__.py
vexor/providers/gemini.py
vexor/providers/local.py
vexor/providers/openai.py
vexor/services/__init__.py
vexor/services/cache_service.py
vexor/services/config_service.py
vexor/services/content_extract_service.py
vexor/services/index_service.py
vexor/services/init_service.py
vexor/services/js_parser.py
vexor/services/keyword_service.py
vexor/services/search_service.py
vexor/services/skill_service.py
vexor/services/system_service.py
vexor/_bundled_skills/vexor-cli/SKILL.md
vexor/_bundled_skills/vexor-cli/references/install-vexor.md
vexor-0.22.0.dist-info/METADATA
vexor-0.22.0.dist-info/WHEEL
vexor-0.22.0.dist-info/entry_points.txt
vexor-0.22.0.dist-info/licenses/LICENSE
vexor-0.22.0.dist-info/RECORD
