Metadata-Version: 2.4
Name: vexor
Version: 0.22.0
Summary: A vector-powered CLI for semantic search over files.
Project-URL: Repository, https://github.com/scarletkc/vexor
Author: scarletkc
License: MIT
License-File: LICENSE
Keywords: ai,cli,file,semantic-search,typer,vector
Classifier: Development Status :: 4 - Beta
Classifier: Environment :: Console
Classifier: Intended Audience :: Developers
Classifier: Intended Audience :: Education
Classifier: Intended Audience :: End Users/Desktop
Classifier: License :: OSI Approved :: MIT License
Classifier: Operating System :: OS Independent
Classifier: Programming Language :: Python
Classifier: Programming Language :: Python :: 3
Classifier: Topic :: Scientific/Engineering :: Information Analysis
Classifier: Topic :: System :: Filesystems
Classifier: Topic :: Text Processing :: Indexing
Classifier: Topic :: Utilities
Requires-Python: >=3.9
Requires-Dist: charset-normalizer>=3.3.0
Requires-Dist: google-genai>=0.5.0
Requires-Dist: numpy>=1.23.0
Requires-Dist: openai>=1.0.0
Requires-Dist: pathspec>=0.12.1
Requires-Dist: pypdf>=4.0.0
Requires-Dist: python-docx>=0.8.11
Requires-Dist: python-dotenv>=1.0.0
Requires-Dist: python-pptx>=0.6.21
Requires-Dist: rank-bm25>=0.2.2
Requires-Dist: rich>=13.0.0
Requires-Dist: scikit-learn>=1.3.0
Requires-Dist: tokenizers>=0.15.0
Requires-Dist: tree-sitter-javascript>=0.23.0
Requires-Dist: tree-sitter-typescript>=0.23.0
Requires-Dist: tree-sitter>=0.23.0
Requires-Dist: typer>=0.9.0
Provides-Extra: dev
Requires-Dist: build>=1.2.1; extra == 'dev'
Requires-Dist: pyinstaller>=6.0.0; extra == 'dev'
Requires-Dist: pytest-cov>=4.1; extra == 'dev'
Requires-Dist: pytest>=7.4; extra == 'dev'
Requires-Dist: twine>=5.1.1; extra == 'dev'
Provides-Extra: flashrank
Requires-Dist: flashrank>=0.2.9; extra == 'flashrank'
Provides-Extra: local
Requires-Dist: fastembed>=0.4.0; extra == 'local'
Provides-Extra: local-cuda
Requires-Dist: fastembed>=0.4.0; extra == 'local-cuda'
Requires-Dist: onnxruntime-gpu>=1.17.0; (platform_system != 'Darwin') and extra == 'local-cuda'
